newrelic_plugins_agent/__init__.py
newrelic_plugins_agent/agent.py
newrelic_plugins_agent/plugins/__init__.py
newrelic_plugins_agent/plugins/base.py
newrelic_plugins_agent/plugins/mongodb.py
newrelic_plugins_agent-1.3.0.dist-info/DESCRIPTION.rst
newrelic_plugins_agent-1.3.0.dist-info/METADATA
newrelic_plugins_agent-1.3.0.dist-info/RECORD
newrelic_plugins_agent-1.3.0.dist-info/WHEEL
newrelic_plugins_agent-1.3.0.dist-info/entry_points.txt
newrelic_plugins_agent-1.3.0.dist-info/metadata.json
newrelic_plugins_agent-1.3.0.dist-info/top_level.txt
opt/newrelic-plugins-agent/LICENSE
opt/newrelic-plugins-agent/README.rst
opt/newrelic-plugins-agent/newrelic-plugins-agent.cfg
opt/newrelic-plugins-agent/newrelic-plugins-agent.deb
opt/newrelic-plugins-agent/newrelic-plugins-agent.rhel
