Metadata-Version: 2.0
Name: newrelic-plugins-agent
Version: 1.3.0
Summary: Python based agent for collecting metrics for NewRelic
Home-page: https://github.com/Roadmunk/newrelic-plugin-agent
Author: Gavin M. Roy
Author-email: gavinmroy@gmail.com
License: BSD
Platform: UNKNOWN
Classifier: Development Status :: 4 - Beta
Classifier: Intended Audience :: System Administrators
Classifier: License :: OSI Approved :: BSD License
Classifier: Operating System :: POSIX
Classifier: Operating System :: POSIX :: Linux
Classifier: Programming Language :: Python :: 2
Classifier: Programming Language :: Python :: 2.6
Classifier: Programming Language :: Python :: 2.7
Classifier: Programming Language :: Python :: 2 :: Only
Classifier: Topic :: System :: Monitoring
Requires-Dist: helper (>=2.2.2)
Requires-Dist: requests (>=2.0.0)
Provides-Extra: mongodb
Requires-Dist: pymongo; extra == 'mongodb'
